cloudmesh_volume-4.1.6-py3.8-nspkg.pth
cloudmesh/volume/Volume.py
cloudmesh/volume/VolumeABC.py
cloudmesh/volume/__init__.py
cloudmesh/volume/__version__.py
cloudmesh/volume/command/__init__.py
cloudmesh/volume/command/volume.py
cloudmesh_volume-4.1.6.dist-info/LICENSE
cloudmesh_volume-4.1.6.dist-info/METADATA
cloudmesh_volume-4.1.6.dist-info/WHEEL
cloudmesh_volume-4.1.6.dist-info/namespace_packages.txt
cloudmesh_volume-4.1.6.dist-info/top_level.txt
cloudmesh_volume-4.1.6.dist-info/RECORD
